[
    {
        "title": "$\\mathbb{R}$ and $\\mathbb{C}$ Number Systems",
        "link": "/notes/real_complex_number_systems",
        "date": "Dec 26, 2017",
        "tags": ["note", "math", "real-analysis", "baby-rudin"],
        "text": [
            "The rational number system $\\mathbb{Q}$ is not the preferred set",
            "of numbers to perform analysis on in regards to convergence,",
            "continuity, differentiation, and integration. This is because of",
            "the inherent gaps found in between numbers irregardless of how",
            "there exists a rational number in between any two other rational",
            "numbers (by taking the average). We therefore use the set of real",
            "numbers $\\mathbb{R}$ to bridge these gaps. Likewise, the set of",
            "complex numbers $\\mathbb{C}$ can also be considered as they",
            "contain the set of real numbers."
        ]
    },
    {
        "title": "Welcome!",
        "link": "/posts/welcome",
        "date": "December 25, 2017",
        "tags": ["blog", "first-post"],
        "text": [
            "##### Salutations Intrepid Explorer",
            "I see you have found your way to my dusty corner of the Internet",
            "and I humbly welcome you into my modest abode. Here is where I",
            "compile my longer term personal projects with my shorter term",
            "chronocides together with blog posts that detail interesting",
            "topics that I have come across and notes I have taken for various",
            "subjects that I am striving to understand. This website is moreso",
            "to organize my thoughts, but is also intended to facilitate the",
            "sharing of knowledge."
        ]
    },
    {
        "title": "Procedural Planets",
        "link": "/projects/procedural-planets",
        "github": "https://github.com/Quangmire/procedural-planets",
        "date": "Dec 25, 2017",
        "tags": ["project", "graphics", "procgen"],
        "text": [
            "Generate planets using 3D Perlin noise",
            "![Planet 1](/static/media/planet1.gif 'Planet 1')"
        ]
    }
]
